gannpy/__init__.py
gannpy/main.py
gannpy/util.py
gannpy-0.1.12.dist-info/METADATA
gannpy-0.1.12.dist-info/WHEEL
gannpy-0.1.12.dist-info/top_level.txt
gannpy-0.1.12.dist-info/RECORD
