Metadata-Version: 2.2
Name: gannpy
Version: 0.1.12
Summary: A package for Gann trading simulation
Author: SAI JAYANTH GUJJALA
Author-email: keshavaradha990@gmail.com
Classifier: Programming Language :: Python :: 3
Classifier: License :: OSI Approved :: MIT License
Classifier: Operating System :: OS Independent
Requires-Python: >=3.9
Requires-Dist: pandas
Dynamic: author
Dynamic: author-email
Dynamic: classifier
Dynamic: description
Dynamic: description-content-type
Dynamic: requires-dist
Dynamic: requires-python
Dynamic: summary
